gpao/__init__.py
gpao/builder.py
gpao/job.py
gpao/project.py
gpao/reader.py
ign_gpao_project_builder-0.12.0.dist-info/METADATA
ign_gpao_project_builder-0.12.0.dist-info/WHEEL
ign_gpao_project_builder-0.12.0.dist-info/top_level.txt
ign_gpao_project_builder-0.12.0.dist-info/RECORD
