Metadata-Version: 2.1
Name: ign-gpao-project-builder
Version: 0.12.0
Summary: Write a json's GPAO file
Home-page: https://github.com/ign-gpao/builder-python.git
Author: Arnaud Birk
Author-email: arnaud.birk@ign.fr
License: MIT
Platform: UNKNOWN
Classifier: License :: OSI Approved :: MIT License
Classifier: Programming Language :: Python :: 3
Classifier: Programming Language :: Python :: 3.8
Requires-Dist: requests
